{
  "/js/app.js": "/js/app.js",
  "/css/app.css": "/css/app.css",
  "/js/form.js": "/js/form.js",
  "/js/form_sitting.js": "/js/form_sitting.js",
  "/js/form_sitting_other.js": "/js/form_sitting_other.js",
  "/js/form_pa2mla.js": "/js/form_pa2mla.js",
  "/js/form_other.js": "/js/form_other.js",
  "/js/form_show.js": "/js/form_show.js",
  "/js/form_other_show.js": "/js/form_other_show.js",
  "/js/employee_index.js": "/js/employee_index.js",
  "/mix.js": "/mix.js",
  "/js/form.1.0.js": "/js/form.1.0.js",
  "/js/form_sitting.1.0.js": "/js/form_sitting.1.0.js",
  "/js/form_show.1.0.js": "/js/form_show.1.0.js",
  "/js/form.1.1.js": "/js/form.1.1.js",
  "/js/form_sitting.1.2.js": "/js/form_sitting.1.2.js",
  "/js/form.1.2.js": "/js/form.1.2.js",
  "/js/form_exemption.js": "/js/form_exemption.js",
  "/js/formexemption_show.1.0.js": "/js/formexemption_show.1.0.js",
  "/js/form_sitting.1.3.js": "/js/form_sitting.1.3.js",
  "/js/home.js": "/js/home.js",
  "/js/home.1.js": "/js/home.1.js",
  "/js/form_sitting.1.4.js": "/js/form_sitting.1.4.js",
  "/js/form.1.4.js": "/js/form.1.4.js",
  "/js/attendace_index.js": "/js/attendace_index.js",
  "/js/attendance_index.js": "/js/attendance_index.js",
  "/js/form.1.5.js": "/js/form.1.5.js",
  "/js/form_other.1.js": "/js/form_other.1.js",
  "/js/form_sitting.1.5.js": "/js/form_sitting.1.5.js",
  "/js/form_sitting_other.1.js": "/js/form_sitting_other.1.js"
}